ipfn/__init__.py
ipfn/ipfn.py
ipfn-1.4.3.dist-info/METADATA
ipfn-1.4.3.dist-info/WHEEL
ipfn-1.4.3.dist-info/top_level.txt
ipfn-1.4.3.dist-info/RECORD
