Metadata-Version: 2.1
Name: ipfn
Version: 1.4.3
Summary: Iterative Proportional Fitting with N dimensions, for python
Home-page: https://github.com/Dirguis/ipfn.git
Author: Damien Forthommme
Author-email: damien2227@hotmail.com
License: MIT
Keywords: iterative proportional fitting ipfp biproportional ras raking scaling
Platform: Any
Classifier: Development Status :: 4 - Beta
Classifier: Intended Audience :: Science/Research
Classifier: Topic :: Software Development :: Build Tools
Classifier: License :: OSI Approved :: MIT License
Classifier: Programming Language :: Python :: 3
Requires-Dist: pandas (>=0.22.0)
Requires-Dist: numpy
